{
  "pool_address": "0x109830a1AAaD605BbF02a9dFA7B0B92EC2FB7dAa",
  "token0": {
    "address": "0x7f39C581F595B53c5cb19bD0b3f8dA6c935E2Ca0",
    "symbol": "wstETH",
    "decimals": 18
  },
  "token1": {
    "address": "0xC02aaA39b223FE8D0A0e5C4F27eAD9083C756Cc2",
    "symbol": "WETH",
    "decimals": 18
  },
  "fee": 100,
  "tick_spacing": 1,
  "start_block": 21714243,
  "end_block": 21930243,
  "block_step": 1000,
  "adaptive_sampling": true,
  "parallel_processing": false,
  "data_points": 217,
  "collection_timestamp": 1740569910,
  "collection_datetime": "2025-02-26 19:38:30",
  "volume_data_available": true
}